infracheck/__init__.py
infracheck/__main__.py
infracheck/functional-test.sh
infracheck/checks/__init__.py
infracheck/checks/dir-present
infracheck/checks/disk-space
infracheck/checks/docker-container-log
infracheck/checks/docker-health
infracheck/checks/domain-expiration
infracheck/checks/false
infracheck/checks/file-present
infracheck/checks/free-ram
infracheck/checks/http
infracheck/checks/influxdb-query
infracheck/checks/load-average
infracheck/checks/load-average-auto
infracheck/checks/ovh-expiration
infracheck/checks/port-open
infracheck/checks/postgres
infracheck/checks/postgres-primary-streaming-status
infracheck/checks/postgres-replica-status
infracheck/checks/printr
infracheck/checks/reminder
infracheck/checks/replication-running
infracheck/checks/smtp_credentials_check.py
infracheck/checks/ssh-command
infracheck/checks/ssh-files-checksum
infracheck/checks/ssh-fingerprint
infracheck/checks/swap-usage-max-percent
infracheck/checks/tls
infracheck/checks/tls-docker-network
infracheck/checks/true
infracheck/checks-tests/disk-space-test.sh
infracheck/checks-tests/free-ram-test.sh
infracheck/checks-tests/http-test.sh
infracheck/checks-tests/load-average-auto-test.sh
infracheck/checks-tests/load-average-test.sh
infracheck/checks-tests/reminder-test.sh
infracheck/checks-tests/swap-usage-max-percent-test.sh
infracheck/configured/.gitkeep
infracheck/infracheck/__init__.py
infracheck/infracheck/bin.py
infracheck/infracheck/config.py
infracheck/infracheck/controller.py
infracheck/infracheck/exceptions.py
infracheck/infracheck/http.py
infracheck/infracheck/model.py
infracheck/infracheck/repository.py
infracheck/infracheck/rkd_support.py
infracheck/infracheck/runner.py
infracheck/infracheck/scheduler.py
infracheck/infracheck/versioning.py
infracheck/infracheck/checklib/__init__.py
infracheck/infracheck/checklib/loadavg.py
infracheck/infracheck/checklib/postgres.py
infracheck/infracheck/checklib/ssh.py
infracheck/template/data-dir-present.json
infracheck-2.1.2.dist-info/AUTHORS
infracheck-2.1.2.dist-info/LICENSE
infracheck-2.1.2.dist-info/METADATA
infracheck-2.1.2.dist-info/WHEEL
infracheck-2.1.2.dist-info/entry_points.txt
infracheck-2.1.2.dist-info/pbr.json
infracheck-2.1.2.dist-info/top_level.txt
infracheck-2.1.2.dist-info/RECORD
